MANIFEST.in
license.txt
readme.txt
setup.py
luxemx/__init__.py
luxemx/luxemx.py
luxemx.egg-info/PKG-INFO
luxemx.egg-info/SOURCES.txt
luxemx.egg-info/dependency_links.txt
luxemx.egg-info/entry_points.txt
luxemx.egg-info/requires.txt
luxemx.egg-info/top_level.txt