Metadata-Version: 1.1
Name: luxemx
Version: 0.0.1
Summary: Extracts specified elements from luxem documents
Home-page: https://github.com/Rendaw/luxemx
Author: Rendaw
Author-email: spoo@zarbosoft.com
License: BSD
Download-URL: https://github.com/Rendaw/luxemx/tarball/v0.0.1
Platform: UNKNOWN
Classifier: Development Status :: 3 - Alpha
Classifier: Environment :: Console
Classifier: Topic :: Text Processing :: Filters
Classifier: License :: OSI Approved :: BSD License
